README.md
setup.py
src/vdk/plugin/notebook/cell.py
src/vdk/plugin/notebook/notebook.py
src/vdk/plugin/notebook/notebook_based_step.py
src/vdk/plugin/notebook/notebook_plugin.py
src/vdk_notebook.egg-info/PKG-INFO
src/vdk_notebook.egg-info/SOURCES.txt
src/vdk_notebook.egg-info/dependency_links.txt
src/vdk_notebook.egg-info/entry_points.txt
src/vdk_notebook.egg-info/requires.txt
src/vdk_notebook.egg-info/top_level.txt