Metadata-Version: 2.1
Name: vdk-notebook
Version: 0.1.752885187
Summary: A VDK plugin for working with notebooks
Home-page: https://github.com/vmware/versatile-data-kit
Classifier: Development Status :: 3 - Alpha
Classifier: License :: OSI Approved :: Apache Software License
Classifier: Programming Language :: Python :: 3.7
Classifier: Programming Language :: Python :: 3.8
Classifier: Programming Language :: Python :: 3.9
Classifier: Programming Language :: Python :: 3.10
Requires-Python: ~=3.7
